README.md
setup.cfg
setup.py
fusion_rsa/__init__.py
fusion_rsa.egg-info/PKG-INFO
fusion_rsa.egg-info/SOURCES.txt
fusion_rsa.egg-info/dependency_links.txt
fusion_rsa.egg-info/not-zip-safe
fusion_rsa.egg-info/requires.txt
fusion_rsa.egg-info/top_level.txt