Metadata-Version: 1.2
Name: fusion-rsa
Version: 0.1
Summary: Python library to compute RDMs from multiple sources.
Home-page: https://github.com/haideraltahan/fusion_rsa
Author: Haider Al-Tahan
Author-email: haideraltahan@gmail.com
License: MIT
Download-URL: https://github.com/haideraltahan/fusion_rsa/archive/0.1.tar.gz
Project-URL: Bug Tracker, https://bugs.example.com/HelloWorld/
Project-URL: Documentation, https://docs.example.com/HelloWorld/
Project-URL: Source Code, https://code.example.com/HelloWorld/
Keywords: representation similarity analysis,representational dissimilarity matrix
Platform: Windows
Platform: Linux
Platform: Solaris
Platform: Mac OS-X
Platform: Unix
Classifier: Development Status :: 3 - Alpha
Classifier: Intended Audience :: Developers
Classifier: Topic :: Software Development :: Build Tools
Classifier: License :: OSI Approved :: MIT License
Classifier: Programming Language :: Python :: 3
Classifier: Programming Language :: Python :: 3.4
Classifier: Programming Language :: Python :: 3.5
Classifier: Programming Language :: Python :: 3.6
Classifier: Programming Language :: Python :: 3.7
Requires-Python: >=3.5
